acft/__init__.py
acft/neural_operator.py
acft-0.1.0.dist-info/METADATA
acft-0.1.0.dist-info/WHEEL
acft-0.1.0.dist-info/entry_points.txt
acft-0.1.0.dist-info/top_level.txt
acft-0.1.0.dist-info/RECORD
