Metadata-Version: 2.4
Name: acft
Version: 0.1.0
Summary: ACFT – Adaptive Cognitive Field Theory engine for stabilizing LLM reasoning (Ollama-ready).
Author-email: Izharuddin Khan <ik2019dec@gmail.com>
Project-URL: Homepage, https://github.com/AiEngineersLabs/acft
Requires-Python: >=3.10
Requires-Dist: numpy>=1.24
Requires-Dist: requests>=2.31
Requires-Dist: pydantic<2.0,>=1.10
Requires-Dist: python-dotenv>=1.0
